langcheck/__init__.py
langcheck/_handle_logs.py
langcheck/stats.py
langcheck/augment/__init__.py
langcheck/augment/_common/_jailbreak_template.py
langcheck/augment/_common/_payload_splitting.py
langcheck/augment/en/__init__.py
langcheck/augment/en/_change_case.py
langcheck/augment/en/_jailbreak_template.py
langcheck/augment/en/_keyboard_typo.py
langcheck/augment/en/_ocr_typo.py
langcheck/augment/en/_payload_splitting.py
langcheck/augment/en/_remove_punctuation.py
langcheck/augment/en/_rephrase.py
langcheck/augment/en/_rephrase_with_system_role_context.py
langcheck/augment/en/_rephrase_with_user_role_context.py
langcheck/augment/en/_synonym.py
langcheck/augment/en/_to_full_width.py
langcheck/augment/en/_gender/__init__.py
langcheck/augment/en/_gender/_gender.py
langcheck/augment/en/_gender/_gender_pronouns.py
langcheck/augment/ja/__init__.py
langcheck/augment/ja/_conv_kana.py
langcheck/augment/ja/_jailbreak_template.py
langcheck/augment/ja/_payload_splitting.py
langcheck/augment/ja/_rephrase_with_system_role_context.py
langcheck/augment/ja/_rephrase_with_user_role_context.py
langcheck/augment/ja/_synonym.py
langcheck/metrics/__init__.py
langcheck/metrics/_pairwise_text_quality_utils.py
langcheck/metrics/custom_text_quality.py
langcheck/metrics/metric_inputs.py
langcheck/metrics/metric_value.py
langcheck/metrics/reference_based_text_quality.py
langcheck/metrics/text_structure.py
langcheck/metrics/de/__init__.py
langcheck/metrics/de/_tokenizers.py
langcheck/metrics/de/_translation.py
langcheck/metrics/de/query_based_text_quality.py
langcheck/metrics/de/reference_based_text_quality.py
langcheck/metrics/de/reference_free_text_quality.py
langcheck/metrics/de/source_based_text_quality.py
langcheck/metrics/en/__init__.py
langcheck/metrics/en/pairwise_text_quality.py
langcheck/metrics/en/query_based_text_quality.py
langcheck/metrics/en/reference_based_text_quality.py
langcheck/metrics/en/reference_free_text_quality.py
langcheck/metrics/en/source_based_text_quality.py
langcheck-0.9.0.dist-info/LICENSE
langcheck-0.9.0.dist-info/METADATA
langcheck-0.9.0.dist-info/WHEEL
langcheck-0.9.0.dist-info/top_level.txt
langcheck-0.9.0.dist-info/RECORD
