Metadata-Version: 2.1
Name: langcheck
Version: 0.9.0
Summary: Simple, Pythonic building blocks to evaluate LLM-based applications
Author-email: Citadel AI <info@citadel.co.jp>
License: MIT License
Project-URL: repository, https://github.com/citadel-ai/langcheck
Keywords: llm,ai,nlp,evaluation,validation,testing
Classifier: License :: OSI Approved :: MIT License
Classifier: Programming Language :: Python :: 3
Requires-Python: >=3.9
License-File: LICENSE
Requires-Dist: dash>=2.11
Requires-Dist: jaconv
Requires-Dist: Jinja2
Requires-Dist: nlpaug
Requires-Dist: nltk>=3.9
Requires-Dist: openai>=1
Requires-Dist: pandas>=1
Requires-Dist: plotly>=5
Requires-Dist: rouge-score>=0.1.2
Requires-Dist: sentence-transformers>=2
Requires-Dist: sentencepiece>=0.1.95
Requires-Dist: tomli; python_version < "3.11"
Requires-Dist: tokenizers>=0.13.2; python_version >= "3.11"
Requires-Dist: torch>=2
Requires-Dist: transformers>=4.6
Requires-Dist: tabulate>=0.9.0
Requires-Dist: omegaconf>=2.3.0
Provides-Extra: de
Provides-Extra: en
Provides-Extra: ja
Requires-Dist: chikkarpy; extra == "ja"
Requires-Dist: fugashi; extra == "ja"
Requires-Dist: janome>=0.3.1; extra == "ja"
Requires-Dist: unidic-lite>=1.0.1; extra == "ja"
Provides-Extra: ja-optional
Requires-Dist: mecab-python3>=1.0.4; extra == "ja-optional"
Requires-Dist: sudachidict-core; extra == "ja-optional"
Requires-Dist: sudachipy; extra == "ja-optional"
Provides-Extra: zh
Requires-Dist: hanlp>=2.1.0b33; extra == "zh"
Provides-Extra: anthropic
Requires-Dist: anthropic; extra == "anthropic"
Provides-Extra: gemini
Requires-Dist: google-generativeai; extra == "gemini"
Provides-Extra: local-llm
Requires-Dist: vllm; extra == "local-llm"
Provides-Extra: all
Requires-Dist: langcheck[de]; extra == "all"
Requires-Dist: langcheck[en]; extra == "all"
Requires-Dist: langcheck[ja]; extra == "all"
Requires-Dist: langcheck[ja-optional]; extra == "all"
Requires-Dist: langcheck[zh]; extra == "all"
Requires-Dist: langcheck[anthropic]; extra == "all"
Requires-Dist: langcheck[gemini]; extra == "all"
Requires-Dist: langcheck[local-llm]; extra == "all"
Provides-Extra: no-local-llm
Requires-Dist: langcheck[de]; extra == "no-local-llm"
Requires-Dist: langcheck[en]; extra == "no-local-llm"
Requires-Dist: langcheck[ja]; extra == "no-local-llm"
Requires-Dist: langcheck[ja-optional]; extra == "no-local-llm"
Requires-Dist: langcheck[zh]; extra == "no-local-llm"
Requires-Dist: langcheck[anthropic]; extra == "no-local-llm"
Requires-Dist: langcheck[gemini]; extra == "no-local-llm"
Provides-Extra: dev
Requires-Dist: ruff>=0.6; extra == "dev"
Requires-Dist: pyright; extra == "dev"
Requires-Dist: pandas-stubs; extra == "dev"
Requires-Dist: pytest; extra == "dev"
Requires-Dist: sphinx; extra == "dev"
Requires-Dist: sphinx-book-theme; extra == "dev"
Requires-Dist: myst-parser; extra == "dev"
Requires-Dist: ipykernel; extra == "dev"
Requires-Dist: sphinxcontrib-youtube; extra == "dev"
